README.md
setup.cfg
setup.py
apm/__init__.py
apm/main.py
python_apm.egg-info/PKG-INFO
python_apm.egg-info/SOURCES.txt
python_apm.egg-info/dependency_links.txt
python_apm.egg-info/entry_points.txt
python_apm.egg-info/requires.txt
python_apm.egg-info/top_level.txt