Metadata-Version: 1.1
Name: python-apm
Version: 1.0.8
Summary: Ansible Package Manager
Home-page: https://github.com/WeslyG/apm
Author: Wesly Allan
Author-email: weslyg22@gmail.com
License: MIT
Keywords: Ansible,Package,APM
Platform: UNKNOWN
Classifier: Programming Language :: Python :: Implementation
Classifier: Programming Language :: Python :: 3
Classifier: Natural Language :: English
Classifier: License :: OSI Approved :: MIT License
Classifier: Operating System :: OS Independent
